aws_assume/__init__.py
aws_assume/_assume.py
aws_assume-0.2.3.dist-info/entry_points.txt
aws_assume-0.2.3.dist-info/LICENSE.txt
aws_assume-0.2.3.dist-info/WHEEL
aws_assume-0.2.3.dist-info/METADATA
aws_assume-0.2.3.dist-info/RECORD
