Metadata-Version: 2.1
Name: aws-assume
Version: 0.2.3
Summary: AWS session token refreshing daemon
Home-page: https://github.com/meeuw/aws_assume
Keywords: AWS,MFA,keyring,keychain,yubikey
Author: Dick Marinus
Author-email: dick@mrns.nl
Requires-Python: >=3.7,<4.0
Classifier: Programming Language :: Python :: 3
Classifier: Programming Language :: Python :: 3.7
Classifier: Programming Language :: Python :: 3.8
Requires-Dist: aws_credential_process (>=0.2.0,<0.3.0)
Requires-Dist: click (==7.0)
Project-URL: Repository, https://github.com/meeuw/aws_assume
